ai_token_chunker/__init__.py
ai_token_chunker/chunker.py
ai_token_chunker/errors.py
ai_token_chunker/image.py
ai_token_chunker/limits.py
ai_token_chunker/providers.py
ai_token_chunker/utils.py
ai_token_chunker-0.1.0.dist-info/licenses/LICENSE
ai_token_chunker-0.1.0.dist-info/METADATA
ai_token_chunker-0.1.0.dist-info/WHEEL
ai_token_chunker-0.1.0.dist-info/top_level.txt
ai_token_chunker-0.1.0.dist-info/RECORD
