Metadata-Version: 2.4
Name: ai-token-chunker
Version: 0.1.0
Summary: Safely split prompts across multiple AI providers without breaking token or byte limits
Author-email: Vikas <your-email@example.com>
License: MIT
Project-URL: Homepage, https://www.npmjs.com/package/ai-token-chunker
Project-URL: Repository, https://github.com/vikaskbh/ai-token-chunker
Classifier: Programming Language :: Python :: 3
Classifier: License :: OSI Approved :: MIT License
Classifier: Operating System :: OS Independent
Requires-Python: >=3.9
License-File: LICENSE
Dynamic: license-file
